hbmqtt/__init__.py
hbmqtt/adapters.py
hbmqtt/broker.py
hbmqtt/client.py
hbmqtt/codecs.py
hbmqtt/errors.py
hbmqtt/session.py
hbmqtt/utils.py
hbmqtt/version.py
hbmqtt/mqtt/__init__.py
hbmqtt/mqtt/connack.py
hbmqtt/mqtt/connect.py
hbmqtt/mqtt/constants.py
hbmqtt/mqtt/disconnect.py
hbmqtt/mqtt/packet.py
hbmqtt/mqtt/pingreq.py
hbmqtt/mqtt/pingresp.py
hbmqtt/mqtt/puback.py
hbmqtt/mqtt/pubcomp.py
hbmqtt/mqtt/publish.py
hbmqtt/mqtt/pubrec.py
hbmqtt/mqtt/pubrel.py
hbmqtt/mqtt/suback.py
hbmqtt/mqtt/subscribe.py
hbmqtt/mqtt/unsuback.py
hbmqtt/mqtt/unsubscribe.py
hbmqtt/mqtt/protocol/__init__.py
hbmqtt/mqtt/protocol/broker_handler.py
hbmqtt/mqtt/protocol/client_handler.py
hbmqtt/mqtt/protocol/handler.py
hbmqtt/plugins/__init__.py
hbmqtt/plugins/authentication.py
hbmqtt/plugins/logging.py
hbmqtt/plugins/manager.py
hbmqtt/plugins/persistence.py
hbmqtt/plugins/topic_checking.py
hbmqtt/plugins/sys/__init__.py
hbmqtt/plugins/sys/broker.py
scripts/__init__.py
scripts/broker_script.py
scripts/default_broker.yaml
scripts/default_client.yaml
scripts/pub_script.py
scripts/sub_script.py
tests/mqtt/__init__.py
tests/mqtt/test_connect.py
tests/mqtt/test_packet.py
tests/mqtt/test_puback.py
tests/mqtt/test_pubcomp.py
tests/mqtt/test_publish.py
tests/mqtt/test_pubrec.py
tests/mqtt/test_pubrel.py
tests/mqtt/test_suback.py
tests/mqtt/test_subscribe.py
tests/mqtt/test_unsuback.py
tests/mqtt/test_unsubscribe.py
tests/mqtt/protocol/__init__.py
tests/mqtt/protocol/test_handler.py
tests/plugins/__init__.py
tests/plugins/passwd
tests/plugins/test_authentication.py
tests/plugins/test_manager.py
tests/plugins/test_persistence.py
tulir_hbmqtt-0.9.7.dev20200404232413.dist-info/METADATA
tulir_hbmqtt-0.9.7.dev20200404232413.dist-info/WHEEL
tulir_hbmqtt-0.9.7.dev20200404232413.dist-info/entry_points.txt
tulir_hbmqtt-0.9.7.dev20200404232413.dist-info/top_level.txt
tulir_hbmqtt-0.9.7.dev20200404232413.dist-info/RECORD
