Metadata-Version: 2.1
Name: tulir-hbmqtt
Version: 0.9.7.dev20200404232413
Summary: MQTT client/broker using Python 3.4 asyncio library
Home-page: https://github.com/beerfactory/hbmqtt
Author: Nicolas Jouanin
Author-email: nico@beerfactory.org
License: MIT
Platform: all
Classifier: Development Status :: 3 - Alpha
Classifier: Intended Audience :: Developers
Classifier: License :: OSI Approved :: MIT License
Classifier: Operating System :: POSIX
Classifier: Operating System :: MacOS
Classifier: Operating System :: Microsoft :: Windows
Classifier: Programming Language :: Python :: 3.4
Classifier: Programming Language :: Python :: 3.5
Classifier: Programming Language :: Python :: 3.6
Classifier: Topic :: Communications
Classifier: Topic :: Internet
Requires-Dist: docopt
Requires-Dist: passlib
Requires-Dist: pyyaml
Requires-Dist: transitions
Requires-Dist: websockets
